iflow_mcp_mcp_server_servicenow-0.1.0.dist-info/licenses/LICENSE
mcp_server_servicenow/__init__.py
mcp_server_servicenow/cli.py
mcp_server_servicenow/nlp.py
mcp_server_servicenow/server.py
iflow_mcp_mcp_server_servicenow-0.1.0.dist-info/METADATA
iflow_mcp_mcp_server_servicenow-0.1.0.dist-info/WHEEL
iflow_mcp_mcp_server_servicenow-0.1.0.dist-info/entry_points.txt
iflow_mcp_mcp_server_servicenow-0.1.0.dist-info/top_level.txt
iflow_mcp_mcp_server_servicenow-0.1.0.dist-info/RECORD
