Metadata-Version: 2.4
Name: iflow-mcp_mcp-server-servicenow
Version: 0.1.0
Summary: ServiceNow MCP Server for natural language interactions with ServiceNow
Author-email: Michael Buckner <michael.buckner@example.com>
License: MIT
Project-URL: Homepage, https://github.com/michaelbuckner/servicenow-mcp
Project-URL: Bug Tracker, https://github.com/michaelbuckner/servicenow-mcp/issues
Project-URL: Documentation, https://github.com/michaelbuckner/servicenow-mcp#readme
Keywords: servicenow,mcp,ai,nlp,automation
Classifier: Development Status :: 4 - Beta
Classifier: Programming Language :: Python :: 3
Classifier: Programming Language :: Python :: 3.8
Classifier: Programming Language :: Python :: 3.9
Classifier: Programming Language :: Python :: 3.10
Classifier: Programming Language :: Python :: 3.11
Classifier: License :: OSI Approved :: MIT License
Classifier: Operating System :: OS Independent
Classifier: Intended Audience :: Developers
Classifier: Topic :: Software Development :: Libraries :: Python Modules
Classifier: Topic :: Internet :: WWW/HTTP
Requires-Python: >=3.8
License-File: LICENSE
Requires-Dist: mcp>=1.0.0
Requires-Dist: httpx>=0.27.0
Requires-Dist: requests>=2.31.0
Requires-Dist: pydantic>=2.0.0
Requires-Dist: python-dotenv>=1.0.0
Provides-Extra: dev
Requires-Dist: pytest>=7.0.0; extra == "dev"
Requires-Dist: pytest-cov>=4.0.0; extra == "dev"
Requires-Dist: black>=23.0.0; extra == "dev"
Requires-Dist: isort>=5.12.0; extra == "dev"
Requires-Dist: mypy>=1.0.0; extra == "dev"
Requires-Dist: flake8>=6.0.0; extra == "dev"
Dynamic: license-file
